http_ok/__init__.py
http_ok/run.py
http_ok-0.1.dist-info/METADATA
http_ok-0.1.dist-info/WHEEL
http_ok-0.1.dist-info/entry_points.txt
http_ok-0.1.dist-info/top_level.txt
http_ok-0.1.dist-info/RECORD
